setup.py
jobspider/__init__.py
jobspider/byr.py
jobspider/dajie.py
jobspider/job51.py
jobspider/lagou.py
jobspider/spider.py
jobspider/zhilian.py
jobspider.egg-info/PKG-INFO
jobspider.egg-info/SOURCES.txt
jobspider.egg-info/dependency_links.txt
jobspider.egg-info/not-zip-safe
jobspider.egg-info/requires.txt
jobspider.egg-info/top_level.txt
jobspider/baseclass/__init__.py
jobspider/baseclass/base_spider.py
jobspider/baseclass/config.py
jobspider/baseclass/database.py
jobspider/baseclass/excel.py
jobspider/baseclass/myredis.py
jobspider/baseclass/send_email.py
jobspider/baseclass/utils/__init__.py
jobspider/baseclass/utils/get_cookies.py
jobspider/baseclass/utils/get_user_agent.py
jobspider/baseclass/utils/joblog.py
jobspider/baseclass/utils/setcolor.py
jobspider/baseclass/utils/store_data.py